carloscar/__init__.py
carloscar/__version__.py
carloscar/py.typed
carloscar-0.0.5.dist-info/LICENSE
carloscar-0.0.5.dist-info/WHEEL
carloscar-0.0.5.dist-info/METADATA
carloscar-0.0.5.dist-info/RECORD
