Metadata-Version: 2.1
Name: carloscar
Version: 0.0.5
Summary: carloscar cli – a command line interface for productivity and every-day tasks
Home-page: https://github.com/kalaspuff/carloscar-cli
License: MIT
Keywords: carloscar,co,cli,carl oscar,carloscar-cli
Author: Carl Oscar Aaro
Author-email: hello@carloscar.com
Requires-Python: >=3.7,<4.0
Classifier: Development Status :: 1 - Planning
Classifier: License :: OSI Approved :: MIT License
Classifier: Programming Language :: Python
Classifier: Programming Language :: Python :: 3
Classifier: Programming Language :: Python :: 3.7
Classifier: Programming Language :: Python :: 3.8
Classifier: Topic :: Software Development
Classifier: Topic :: Software Development :: Build Tools
Classifier: Topic :: Software Development :: Code Generators
Classifier: Topic :: Software Development :: Testing
Classifier: Topic :: System :: Systems Administration
Classifier: Topic :: Utilities
Classifier: Typing :: Typed
Project-URL: Repository, https://github.com/kalaspuff/carloscar-cli
